diffractio/__init__.py
diffractio/config.py
diffractio/scalar_fields_X.py
diffractio/scalar_fields_XY.py
diffractio/scalar_fields_XYZ.py
diffractio/scalar_fields_XZ.py
diffractio/scalar_fields_Z.py
diffractio/scalar_masks_X.py
diffractio/scalar_masks_XY.py
diffractio/scalar_masks_XYZ.py
diffractio/scalar_masks_XZ.py
diffractio/scalar_sources_X.py
diffractio/scalar_sources_XY.py
diffractio/utils_common.py
diffractio/utils_drawing.py
diffractio/utils_math.py
diffractio/utils_multiprocessing.py
diffractio/utils_optics.py
diffractio/utils_slicer_deprecated.py
diffractio/utils_tests.py
diffractio/vector_fields_X.py
diffractio/vector_fields_XY.py
diffractio/vector_fields_XYZ.py
diffractio/vector_fields_XZ.py
diffractio/vector_fields_Z.py
diffractio/vector_masks_XY.py
diffractio/vector_sources_XY.py
diffractio-0.2.4.dist-info/AUTHORS.rst
diffractio-0.2.4.dist-info/LICENSE
diffractio-0.2.4.dist-info/METADATA
diffractio-0.2.4.dist-info/WHEEL
diffractio-0.2.4.dist-info/entry_points.txt
diffractio-0.2.4.dist-info/top_level.txt
diffractio-0.2.4.dist-info/RECORD
