Metadata-Version: 2.1
Name: diffractio
Version: 0.2.4
Summary: Optical Diffraction and Interference (scalar and vectorial)
Home-page: https://bitbucket.org/optbrea/diffractio/src/master/
Author: Luis Miguel Sanchez Brea
Author-email: optbrea@ucm.es
License: MIT license
Keywords: diffractio,optics,diffraction,interference,BPM,WPM,CZT,RS,VRS
Platform: UNKNOWN
Classifier: Development Status :: 4 - Beta
Classifier: Intended Audience :: Science/Research
Classifier: License :: OSI Approved :: MIT License
Classifier: Natural Language :: English
Classifier: Programming Language :: Python :: 3
Classifier: Programming Language :: Python :: 3.8
Classifier: Programming Language :: Python :: 3.9
Classifier: Programming Language :: Python :: 3.10
License-File: LICENSE
License-File: AUTHORS.rst
Requires-Dist: Pillow
Requires-Dist: ipympl
Requires-Dist: ipywidgets
Requires-Dist: numexpr
Requires-Dist: opencv-python
Requires-Dist: pandas
Requires-Dist: py-pol
Requires-Dist: screeninfo
